dirac_graph/__init__.py
dirac_graph-1.3.7.dist-info/LICENSE
dirac_graph-1.3.7.dist-info/METADATA
dirac_graph-1.3.7.dist-info/WHEEL
dirac_graph-1.3.7.dist-info/top_level.txt
dirac_graph-1.3.7.dist-info/RECORD
