Metadata-Version: 2.1
Name: dirac_graph
Version: 1.3.7
Summary: Computational spectral geometry on finite graphs
Home-page: https://github.com/pulquero/dirac_graph
Author: Mark Hale
License: MIT
Classifier: Programming Language :: Python :: 3
Classifier: License :: OSI Approved :: MIT License
Classifier: Operating System :: OS Independent
Requires-Python: >=3.6
License-File: LICENSE
